sindri_labs/__init__.py
sindri_labs/sindri.py
sindri_labs-0.1.0a12.dist-info/LICENSE
sindri_labs-0.1.0a12.dist-info/METADATA
sindri_labs-0.1.0a12.dist-info/WHEEL
sindri_labs-0.1.0a12.dist-info/RECORD
