Metadata-Version: 2.1
Name: sindri-labs
Version: 0.1.0a12
Summary: Sindri Python SDK
Home-page: https://sindri.app
License: MIT
Author: Sindri Labs
Requires-Python: >=3.10,<4.0
Classifier: License :: OSI Approved :: MIT License
Classifier: Operating System :: OS Independent
Classifier: Programming Language :: Python :: 3
Classifier: Programming Language :: Python :: 3.10
Classifier: Programming Language :: Python :: 3.11
Classifier: Programming Language :: Python :: 3.12
Requires-Dist: requests (>=2.13.0,<3.0.0)
Project-URL: Repository, https://github.com/Sindri-Labs/sindri-python
